README.rst
setup.cfg
setup.py
fowler/__init__.py
fowler.switchboard.egg-info/PKG-INFO
fowler.switchboard.egg-info/SOURCES.txt
fowler.switchboard.egg-info/dependency_links.txt
fowler.switchboard.egg-info/entry_points.txt
fowler.switchboard.egg-info/namespace_packages.txt
fowler.switchboard.egg-info/not-zip-safe
fowler.switchboard.egg-info/requires.txt
fowler.switchboard.egg-info/top_level.txt
fowler/switchboard/__init__.py
fowler/switchboard/io.py
fowler/switchboard/main.py
fowler/switchboard/options.py
fowler/switchboard/swda.py
fowler/switchboard/util.py
test/test_io.py