Metadata-Version: 1.1
Name: fowler.switchboard
Version: 0.1dev
Summary: A wrapper around Christopher Potts' swda.py
Home-page: http://www.eecs.qmul.ac.uk/~dm303/
Author: Dmitrijs Milajevs, Christopher Potts
Author-email: dimazest@gmail.com
License: Creative Commons Attribution-NonCommercial-ShareAlike 3.0 Unported License
Platform: UNKNOWN
Classifier: Development Status :: 3 - Alpha
Classifier: Intended Audience :: Developers
Classifier: Intended Audience :: Science/Research
Classifier: License :: OSI Approved :: MIT License
Classifier: Operating System :: POSIX
Classifier: Operating System :: Microsoft :: Windows
Classifier: Operating System :: MacOS :: MacOS X
Classifier: Topic :: Utilities
Classifier: Programming Language :: Python :: 2
Classifier: Programming Language :: Python :: 3
